{
  "type": "Program",
  "start": 0,
  "end": 474,
  "loc": {
    "start": {
      "line": 1,
      "column": 0
    },
    "end": {
      "line": 22,
      "column": 0
    }
  },
  "sourceType": "module",
  "body": [
    {
      "type": "ImportDeclaration",
      "start": 0,
      "end": 56,
      "loc": {
        "start": {
          "line": 1,
          "column": 0
        },
        "end": {
          "line": 1,
          "column": 56
        }
      },
      "specifiers": [
        {
          "type": "ImportDefaultSpecifier",
          "start": 7,
          "end": 26,
          "loc": {
            "start": {
              "line": 1,
              "column": 7
            },
            "end": {
              "line": 1,
              "column": 26
            }
          },
          "local": {
            "type": "Identifier",
            "start": 7,
            "end": 26,
            "loc": {
              "start": {
                "line": 1,
                "column": 7
              },
              "end": {
                "line": 1,
                "column": 26
              }
            },
            "name": "SerializerInterface"
          }
        }
      ],
      "importKind": "value",
      "source": {
        "type": "Literal",
        "start": 32,
        "end": 55,
        "loc": {
          "start": {
            "line": 1,
            "column": 32
          },
          "end": {
            "line": 1,
            "column": 55
          }
        },
        "value": "./SerializerInterface",
        "rawValue": "./SerializerInterface",
        "raw": "'./SerializerInterface'"
      },
      "trailingComments": [
        {
          "type": "Block",
          "value": "*\n * Any serializer implementing this interface will access to a serializer at runtime.\n *\n * @interface\n ",
          "start": 58,
          "end": 168,
          "loc": {
            "start": {
              "line": 3,
              "column": 0
            },
            "end": {
              "line": 7,
              "column": 3
            }
          },
          "range": [
            58,
            168
          ]
        }
      ]
    },
    {
      "type": "ExportDefaultDeclaration",
      "start": 169,
      "end": 473,
      "loc": {
        "start": {
          "line": 8,
          "column": 0
        },
        "end": {
          "line": 21,
          "column": 1
        }
      },
      "declaration": {
        "type": "ClassDeclaration",
        "start": 184,
        "end": 473,
        "loc": {
          "start": {
            "line": 8,
            "column": 15
          },
          "end": {
            "line": 21,
            "column": 1
          }
        },
        "id": {
          "type": "Identifier",
          "start": 190,
          "end": 214,
          "loc": {
            "start": {
              "line": 8,
              "column": 21
            },
            "end": {
              "line": 8,
              "column": 45
            }
          },
          "name": "SerializerAwareInterface",
          "leadingComments": null
        },
        "superClass": {
          "type": "Identifier",
          "start": 223,
          "end": 242,
          "loc": {
            "start": {
              "line": 8,
              "column": 54
            },
            "end": {
              "line": 8,
              "column": 73
            }
          },
          "name": "SerializerInterface"
        },
        "body": {
          "type": "ClassBody",
          "start": 243,
          "end": 473,
          "loc": {
            "start": {
              "line": 8,
              "column": 74
            },
            "end": {
              "line": 21,
              "column": 1
            }
          },
          "body": [
            {
              "type": "Identifier",
              "start": 318,
              "end": 330,
              "loc": {
                "start": {
                  "line": 13,
                  "column": 4
                },
                "end": {
                  "line": 13,
                  "column": 16
                }
              },
              "computed": false,
              "key": {
                "type": "Identifier",
                "start": 318,
                "end": 329,
                "loc": {
                  "start": {
                    "line": 13,
                    "column": 4
                  },
                  "end": {
                    "line": 13,
                    "column": 15
                  }
                },
                "name": "_serializer",
                "leadingComments": null
              },
              "static": false,
              "value": null,
              "leadingComments": [
                {
                  "type": "Block",
                  "value": "*\n     * @type {SerializerInterface}\n     * @protected\n     ",
                  "start": 249,
                  "end": 313,
                  "loc": {
                    "start": {
                      "line": 9,
                      "column": 4
                    },
                    "end": {
                      "line": 12,
                      "column": 7
                    }
                  },
                  "range": [
                    249,
                    313
                  ]
                }
              ],
              "trailingComments": [
                {
                  "type": "Block",
                  "value": "*\n     * @param {SerializerInterface} serializer\n     ",
                  "start": 336,
                  "end": 394,
                  "loc": {
                    "start": {
                      "line": 15,
                      "column": 4
                    },
                    "end": {
                      "line": 17,
                      "column": 7
                    }
                  },
                  "range": [
                    336,
                    394
                  ]
                }
              ]
            },
            {
              "type": "MethodDefinition",
              "start": 399,
              "end": 471,
              "loc": {
                "start": {
                  "line": 18,
                  "column": 4
                },
                "end": {
                  "line": 20,
                  "column": 5
                }
              },
              "computed": false,
              "key": {
                "type": "Identifier",
                "start": 399,
                "end": 412,
                "loc": {
                  "start": {
                    "line": 18,
                    "column": 4
                  },
                  "end": {
                    "line": 18,
                    "column": 17
                  }
                },
                "name": "setSerializer",
                "leadingComments": null
              },
              "static": false,
              "kind": "method",
              "value": {
                "type": "FunctionExpression",
                "start": 412,
                "end": 471,
                "loc": {
                  "start": {
                    "line": 18,
                    "column": 17
                  },
                  "end": {
                    "line": 20,
                    "column": 5
                  }
                },
                "id": null,
                "generator": false,
                "expression": false,
                "async": false,
                "params": [
                  {
                    "type": "Identifier",
                    "start": 413,
                    "end": 423,
                    "loc": {
                      "start": {
                        "line": 18,
                        "column": 18
                      },
                      "end": {
                        "line": 18,
                        "column": 28
                      }
                    },
                    "name": "serializer"
                  }
                ],
                "body": {
                  "type": "BlockStatement",
                  "start": 425,
                  "end": 471,
                  "loc": {
                    "start": {
                      "line": 18,
                      "column": 30
                    },
                    "end": {
                      "line": 20,
                      "column": 5
                    }
                  },
                  "body": [
                    {
                      "type": "ExpressionStatement",
                      "start": 435,
                      "end": 465,
                      "loc": {
                        "start": {
                          "line": 19,
                          "column": 8
                        },
                        "end": {
                          "line": 19,
                          "column": 38
                        }
                      },
                      "expression": {
                        "type": "AssignmentExpression",
                        "start": 435,
                        "end": 464,
                        "loc": {
                          "start": {
                            "line": 19,
                            "column": 8
                          },
                          "end": {
                            "line": 19,
                            "column": 37
                          }
                        },
                        "operator": "=",
                        "left": {
                          "type": "MemberExpression",
                          "start": 435,
                          "end": 451,
                          "loc": {
                            "start": {
                              "line": 19,
                              "column": 8
                            },
                            "end": {
                              "line": 19,
                              "column": 24
                            }
                          },
                          "object": {
                            "type": "ThisExpression",
                            "start": 435,
                            "end": 439,
                            "loc": {
                              "start": {
                                "line": 19,
                                "column": 8
                              },
                              "end": {
                                "line": 19,
                                "column": 12
                              }
                            }
                          },
                          "property": {
                            "type": "Identifier",
                            "start": 440,
                            "end": 451,
                            "loc": {
                              "start": {
                                "line": 19,
                                "column": 13
                              },
                              "end": {
                                "line": 19,
                                "column": 24
                              }
                            },
                            "name": "_serializer"
                          },
                          "computed": false
                        },
                        "right": {
                          "type": "Identifier",
                          "start": 454,
                          "end": 464,
                          "loc": {
                            "start": {
                              "line": 19,
                              "column": 27
                            },
                            "end": {
                              "line": 19,
                              "column": 37
                            }
                          },
                          "name": "serializer"
                        }
                      }
                    }
                  ]
                }
              },
              "leadingComments": [
                {
                  "type": "Block",
                  "value": "*\n     * @param {SerializerInterface} serializer\n     ",
                  "start": 336,
                  "end": 394,
                  "loc": {
                    "start": {
                      "line": 15,
                      "column": 4
                    },
                    "end": {
                      "line": 17,
                      "column": 7
                    }
                  },
                  "range": [
                    336,
                    394
                  ]
                }
              ]
            }
          ]
        },
        "leadingComments": [
          {
            "type": "Block",
            "value": "*\n * Any serializer implementing this interface will access to a serializer at runtime.\n *\n * @interface\n ",
            "start": 58,
            "end": 168,
            "loc": {
              "start": {
                "line": 3,
                "column": 0
              },
              "end": {
                "line": 7,
                "column": 3
              }
            },
            "range": [
              58,
              168
            ]
          }
        ],
        "trailingComments": []
      },
      "leadingComments": [
        {
          "type": "Block",
          "value": "*\n * Any serializer implementing this interface will access to a serializer at runtime.\n *\n * @interface\n ",
          "start": 58,
          "end": 168,
          "loc": {
            "start": {
              "line": 3,
              "column": 0
            },
            "end": {
              "line": 7,
              "column": 3
            }
          },
          "range": [
            58,
            168
          ]
        }
      ]
    }
  ]
}